<?xml version="1.0" encoding="utf-8" ?>
<dwsync>
<file name="fckconstants.js" server="C:/xampp/htdocs/WeDoAn/" local="127182976920000000" remote="127182976920000000" />
<file name="fckeditorapi.js" server="C:/xampp/htdocs/WeDoAn/" local="127182976920000000" remote="127182976920000000" />
<file name="fckjscoreextensions.js" server="C:/xampp/htdocs/WeDoAn/" local="127182976920000000" remote="127182976920000000" />
<file name="fckscriptloader.js" server="C:/xampp/htdocs/WeDoAn/" local="127182976920000000" remote="127182976920000000" />
<file name="fckconstants.js" server="C:/wamp/www/WeDoAn/" local="127182976904687500" remote="127182976900000000" />
<file name="fckeditorapi.js" server="C:/wamp/www/WeDoAn/" local="127182976905000000" remote="127182976900000000" />
<file name="fckjscoreextensions.js" server="C:/wamp/www/WeDoAn/" local="127182976905781250" remote="127182976900000000" />
<file name="fckscriptloader.js" server="C:/wamp/www/WeDoAn/" local="127182976906718750" remote="127182976900000000" />
<file name="fckconstants.js" server="C:/wamp/www/web/" local="127182976904687500" remote="127182976900000000" />
<file name="fckeditorapi.js" server="C:/wamp/www/web/" local="127182976905000000" remote="127182976900000000" />
<file name="fckjscoreextensions.js" server="C:/wamp/www/web/" local="127182976905781250" remote="127182976900000000" />
<file name="fckscriptloader.js" server="C:/wamp/www/web/" local="127182976906718750" remote="127182976900000000" />
<file name="fckconstants.js" server="C:/xampp/htdocs/Web/" local="127182976904687500" remote="127182976900000000" />
<file name="fckeditorapi.js" server="C:/xampp/htdocs/Web/" local="127182976905000000" remote="127182976900000000" />
<file name="fckjscoreextensions.js" server="C:/xampp/htdocs/Web/" local="127182976905781250" remote="127182976900000000" />
<file name="fckscriptloader.js" server="C:/xampp/htdocs/Web/" local="127182976906718750" remote="127182976900000000" />
</dwsync>